grandprix/__init__.py
grandprix/ergast/Ergast.py
grandprix/ergast/START_YEAR.py
grandprix/ergast/__init__.py
grandprix/ergast/get_drivers.py
grandprix/ergast/get_ergast_data.py
grandprix/ergast/get_num_rounds.py
grandprix/ergast/get_schedule.py
grandprix/ergast/json/__init__.py
grandprix/ergast/json/convert_json_to_df.py
grandprix/ergast/json/get_ergast_json.py
grandprix/utils/Filter.py
grandprix/utils/__init__.py
grandprix/utils/bring_columns_to_front.py
grandprix/utils/dict_of_dicts_to_df.py
grandprix/utils/merge_data.py
grandprix/utils/aggregate/Agg.py
grandprix/utils/aggregate/__init__.py
grandprix/utils/aggregate/aggregate.py
grandprix-0.1.2.dist-info/licenses/LICENSE
grandprix-0.1.2.dist-info/METADATA
grandprix-0.1.2.dist-info/WHEEL
grandprix-0.1.2.dist-info/top_level.txt
grandprix-0.1.2.dist-info/RECORD
