Metadata-Version: 2.4
Name: grandprix
Version: 0.1.2
Summary: A Python package for Formula 1 data analysis and visualization.
Home-page: https://github.com/idin/grandprix
Author: Idin K
Author-email: python@idin.net
License: CFL-1.0
Classifier: Programming Language :: Python :: 3
Classifier: Operating System :: OS Independent
Classifier: License :: Other/Proprietary License
Requires-Python: >=3.8
License-File: LICENSE
Requires-Dist: pandas
Requires-Dist: numpy
Dynamic: author
Dynamic: author-email
Dynamic: classifier
Dynamic: description
Dynamic: description-content-type
Dynamic: home-page
Dynamic: license
Dynamic: license-file
Dynamic: requires-dist
Dynamic: requires-python
Dynamic: summary
